{
    "Ar36": {
        "error": 0.00099388201040060764, 
        "fit": "parabolic", 
        "value": 0.00076790445195864642
    }, 
    "Ar37": {
        "error": 0.13757770684217088, 
        "fit": "linear", 
        "value": 0.033255870917682562
    }, 
    "Ar38": {
        "error": 0.12050315556070944, 
        "fit": "linear", 
        "value": -0.087456291849028783
    }, 
    "Ar39": {
        "error": 0.063314229134710895, 
        "fit": "parabolic", 
        "value": 0.005714173872266512
    }, 
    "Ar40": {
        "error": 0.15354562675838029, 
        "fit": "parabolic", 
        "value": 0.38458781102775386
    }, 
    "Ar41": {
        "error": 0.13597247027087458, 
        "fit": "average_SEM", 
        "value": -0.041705790378861518
    }
}