{
    "AX": {
        "error": 0.06287666944278107, 
        "fit": "average_SEM", 
        "value": -0.019239844382617673
    }, 
    "CDD": {
        "error": 3.734408092675485e-05, 
        "fit": "average_SEM", 
        "value": 9.500906162429602e-06
    }, 
    "H1": {
        "error": 0.13147635760900728, 
        "fit": "average_SEM", 
        "value": 0.05064658983077
    }, 
    "H2": {
        "error": 0.13071359796089677, 
        "fit": "average_SEM", 
        "value": -0.040040798732985015
    }, 
    "L1": {
        "error": 0.11734685563336522, 
        "fit": "average_SEM", 
        "value": -0.08042934793953059
    }, 
    "L2": {
        "error": 0.13376814182334526, 
        "fit": "average_SEM", 
        "value": 0.024007069168631764
    }
}