{
    "AX": {
        "error": 0.05669354878023102, 
        "fit": "average_SEM", 
        "value": -0.01593659744855055
    }, 
    "CDD": {
        "error": 0.00012092399682344998, 
        "fit": "average_SEM", 
        "value": 7.903026586670118e-05
    }, 
    "H1": {
        "error": 0.13897468139321809, 
        "fit": "average_SEM", 
        "value": 0.045438456400006544
    }, 
    "H2": {
        "error": 0.13189982610677334, 
        "fit": "average_SEM", 
        "value": -0.29833807293325665
    }, 
    "L1": {
        "error": 0.10944558546185645, 
        "fit": "average_SEM", 
        "value": -0.0817854688136625
    }, 
    "L2": {
        "error": 0.14959741394261394, 
        "fit": "average_SEM", 
        "value": -0.0036012750473067476
    }
}