{
    "AX": {
        "error": 0.05781542317675712, 
        "fit": "average_SEM", 
        "value": -0.02796624364758221
    }, 
    "CDD": {
        "error": 0.00016060497949339493, 
        "fit": "average_SEM", 
        "value": 0.0001567649553180672
    }, 
    "H1": {
        "error": 0.11870848754998839, 
        "fit": "average_SEM", 
        "value": 0.047779347698572866
    }, 
    "H2": {
        "error": 0.13653909014360613, 
        "fit": "average_SEM", 
        "value": -0.00803712053069224
    }, 
    "L1": {
        "error": 0.13514377839556885, 
        "fit": "average_SEM", 
        "value": -0.05656599736248609
    }, 
    "L2": {
        "error": 0.1506312000803196, 
        "fit": "average_SEM", 
        "value": 0.016475880741685007
    }
}