{
    "AX": {
        "error": 0.052080275638345636, 
        "fit": "average_SEM", 
        "value": -0.02867600881986113
    }, 
    "CDD": {
        "error": 9.160708947991559e-05, 
        "fit": "average_SEM", 
        "value": 5.70054369745776e-05
    }, 
    "H1": {
        "error": 0.13226753657300852, 
        "fit": "average_SEM", 
        "value": 0.053647018063606486
    }, 
    "H2": {
        "error": 0.1572059176861295, 
        "fit": "average_SEM", 
        "value": -0.03475831739294032
    }, 
    "L1": {
        "error": 0.13311717434632905, 
        "fit": "average_SEM", 
        "value": -0.07227865522792046
    }, 
    "L2": {
        "error": 0.13756455465379935, 
        "fit": "average_SEM", 
        "value": 0.0037228382541798057
    }
}