{
    "AX": {
        "error": 0.06546915132420922, 
        "fit": "average_SEM", 
        "value": -0.029048069274156457
    }, 
    "CDD": {
        "error": 0.00011939428814132714, 
        "fit": "average_SEM", 
        "value": 7.94621255610966e-05
    }, 
    "H1": {
        "error": 0.13556688713475035, 
        "fit": "average_SEM", 
        "value": 0.04102892245088394
    }, 
    "H2": {
        "error": 0.12395779313702887, 
        "fit": "average_SEM", 
        "value": -0.04534417696348909
    }, 
    "L1": {
        "error": 0.11271849682430485, 
        "fit": "average_SEM", 
        "value": -0.06307107757828716
    }, 
    "L2": {
        "error": 0.14164005623298026, 
        "fit": "average_SEM", 
        "value": -0.006642393587389961
    }
}