{
    "AX": {
        "error": 0.052965540948034726, 
        "fit": "average_SEM", 
        "value": -0.03639148085332838
    }, 
    "CDD": {
        "error": 7.952876342854496e-05, 
        "fit": "average_SEM", 
        "value": 4.836824955418706e-05
    }, 
    "H1": {
        "error": 0.13333373671724097, 
        "fit": "average_SEM", 
        "value": 0.01457816685950901
    }, 
    "H2": {
        "error": 0.14601828295134736, 
        "fit": "average_SEM", 
        "value": -0.3567481023983823
    }, 
    "L1": {
        "error": 0.13963042757685087, 
        "fit": "average_SEM", 
        "value": -0.12786338188064594
    }, 
    "L2": {
        "error": 0.1457588193052824, 
        "fit": "average_SEM", 
        "value": -0.1584529735924055
    }
}