{
    "Ar36": {
        "error": 0.001148770818918269, 
        "fit": "linear", 
        "value": 0.0054486339029385135
    }, 
    "Ar37": {
        "error": 0.13635703540315944, 
        "fit": "linear", 
        "value": 0.15321031627352574
    }, 
    "Ar38": {
        "error": 0.15404881390537561, 
        "fit": "linear", 
        "value": 0.81157723170703466
    }, 
    "Ar39": {
        "error": 0.096313544266061174, 
        "fit": "linear", 
        "value": 70.036795960095617
    }, 
    "Ar40": {
        "error": 0.36408635613341572, 
        "fit": "linear", 
        "value": 773.98206192864768
    }, 
    "Ar41": {
        "error": 0.12039465982206941, 
        "fit": "average_SEM", 
        "value": -0.014379474256404338
    }
}